{
// CGRateS Configuration file


"general": {
	"reply_timeout": "30s",
},

"logger": {
	"level": 7
},

"listen": {
	"rpc_json": ":2012",
	"rpc_gob": ":2013",
	"http": ":2080",
},


"data_db": {
	"db_type": "mongo",
	"db_name": "10",
	"db_port": 27017,
},

"stor_db": {
	"db_type": "mongo",
	"db_name": "10",
	"db_port": 27017,
	"db_password": "",
},
"caches":{
	"partitions": {
		"*resource_profiles": {"limit": 10000, "ttl":"", "precache": true},
		"*resources": {"limit": 10000, "ttl":"", "precache": true},
		"*statqueues": {"limit": 10000, "ttl":"", "precache": true},
		"*statqueue_profiles": {"limit": 10000, "ttl":"", "precache": true,"precache_filters":["*string:~*req.id:Stats2"]},
		"*thresholds": {"limit": 10000, "ttl":"", "precache": true},
		"*threshold_profiles": {"limit": 10000, "ttl":"", "precache": true},
		"*filters": {"limit": 10000, "ttl":"", "precache": true},
		"*route_profiles": {"limit": 10000, "ttl":"", "precache": true, "precache_filters": ["*prefix:~*req.id:ROUTE_QOS"]},
		"*attribute_profiles": {"limit": 10000, "ttl":"", "precache": true, "precache_filters": ["*prefix:~*req.id:ATTR_1003"]},
		"*resource_filter_indexes" :{"limit": 10000, "ttl":"", "precache": true},
		"*stat_filter_indexes" : {"limit": 10000, "ttl":"", "precache": true},
		"*threshold_filter_indexes" : {"limit": 10000, "ttl":"", "precache": true},
		"*route_filter_indexes" : {"limit": 10000, "ttl":"", "precache": true},
		"*attribute_filter_indexes" : {"limit": 10000, "ttl":"", "precache": true},
		"*charger_filter_indexes" : {"limit": 10000, "ttl":"", "precache": true},
	},
},


"migrator": {
	"out_datadb_type": "mongo",
	"out_datadb_port": "27017",
	"out_datadb_name": "10",
	"users_filters":["Account"],
},


"admins": {
	"enabled": true,
},


}
